iplscore/__init__.py
iplscore/iplscore.py
iplscore-0.0.6.dist-info/METADATA
iplscore-0.0.6.dist-info/WHEEL
iplscore-0.0.6.dist-info/top_level.txt
iplscore-0.0.6.dist-info/RECORD
