Metadata-Version: 2.1
Name: iplscore
Version: 0.0.6
Summary: It Displays Cricket Score
Home-page: UNKNOWN
Author: Chiranjeev Mishra(chirrumishra)
Author-email: chirrumishra@gmail.com
License: UNKNOWN
Keywords: python,cricket,ipl,iplscore
Platform: UNKNOWN
Classifier: Development Status :: 1 - Planning
Classifier: Intended Audience :: Developers
Classifier: Programming Language :: Python :: 3
Classifier: Operating System :: Unix
Classifier: Operating System :: MacOS :: MacOS X
Classifier: Operating System :: Microsoft :: Windows
Requires-Dist: bs4
Requires-Dist: requests
